tests/__init__.py
tests/test_cart.py
tests/test_cue.py
tests/test_cue_chunk.py
tests/test_data.py
tests/test_format.py
tests/test_label.py
tests/test_labelled_text.py
tests/test_list.py
tests/test_utils.py
tests/test_wave.py
tests/waveparser.py
wave_chunk_parser/__init__.py
wave_chunk_parser/chunks.py
wave_chunk_parser/exceptions.py
wave_chunk_parser/utils.py
wave_chunk_parser-1.5.0.dist-info/LICENSE
wave_chunk_parser-1.5.0.dist-info/METADATA
wave_chunk_parser-1.5.0.dist-info/WHEEL
wave_chunk_parser-1.5.0.dist-info/top_level.txt
wave_chunk_parser-1.5.0.dist-info/RECORD
