Metadata-Version: 2.1
Name: wave-chunk-parser
Version: 1.5.0
Summary: Parses and writes WAVE file chunks
Home-page: https://github.com/steelegbr/wave-chunk-parser
Author: Marc Steele
Author-email: steelegbr@gmail.com
Classifier: Programming Language :: Python :: 3
Classifier: License :: OSI Approved :: Apache Software License
Classifier: Operating System :: OS Independent
Requires-Python: >=3.7
License-File: LICENSE
Requires-Dist: numpy
Requires-Dist: unidecode
